main.py
xlsx_lib/domain/__init__.py
xlsx_lib/domain/abs/AbsCellValueKind.py
xlsx_lib/domain/abs/AbsData.py
xlsx_lib/domain/abs/AbsSheet.py
xlsx_lib/domain/abs/Problem.py
xlsx_lib/domain/autodiagnosis/AutodiagnosisCellValueKind.py
xlsx_lib/domain/autodiagnosis/AutodiagnosisData.py
xlsx_lib/domain/autodiagnosis/AutodiagnosisSheet.py
xlsx_lib/domain/autodiagnosis/Fault.py
xlsx_lib/domain/components/Component.py
xlsx_lib/domain/components/ComponentsData.py
xlsx_lib/domain/components/ComponentsSheet.py
xlsx_lib/domain/distribution/DataBlock.py
xlsx_lib/domain/distribution/DistributionCellValueTypes.py
xlsx_lib/domain/distribution/DistributionData.py
xlsx_lib/domain/distribution/DistributionSheet.py
xlsx_lib/domain/electronic/component_attribute.py
xlsx_lib/domain/electronic/electronic_element.py
xlsx_lib/domain/electronic/electronic_sheet.py
xlsx_lib/domain/electronic/electronic_value_types.py
xlsx_lib/domain/electronic/element_component.py
xlsx_lib/domain/engine/element_attribute.py
xlsx_lib/domain/engine/engine_cell_value_types.py
xlsx_lib/domain/engine/engine_section.py
xlsx_lib/domain/engine/engine_sheet.py
xlsx_lib/domain/engine/section_element.py
xlsx_lib/domain/frame/complex_frame_element_error.py
xlsx_lib/domain/frame/element_part.py
xlsx_lib/domain/frame/frame_cell_value_types.py
xlsx_lib/domain/frame/frame_element.py
xlsx_lib/domain/frame/frame_sheet.py
xlsx_lib/domain/generic_replacements/generic_replacement_sheet.py
xlsx_lib/domain/generic_replacements/replacement.py
xlsx_lib/domain/generic_replacements/replacement_part.py
xlsx_lib/domain/hiss_immobilizer/HissImmobilizerCellValueKind.py
xlsx_lib/domain/hiss_immobilizer/HissImmobilizerData.py
xlsx_lib/domain/hiss_immobilizer/HissImmobilizerSheet.py
xlsx_lib/domain/hiss_immobilizer/Problem.py
xlsx_lib/domain/motorcycle_model/MotorcycleModelWorkbook.py
xlsx_lib/domain/motorcycle_model/SHEETNAMES_RELATIONSHIPS.py
xlsx_lib/domain/motorcycle_model/Sheetnames.py
xlsx_lib_infomoto-0.8.4.dist-info/WHEEL
xlsx_lib_infomoto-0.8.4.dist-info/METADATA
xlsx_lib_infomoto-0.8.4.dist-info/RECORD
