Metadata-Version: 2.1
Name: xlsx-lib-infomoto
Version: 0.8.4
Summary: 
Author: tomasdarioam
Author-email: tomasdarioam@protonmail.com
Requires-Python: >=3.9,<4.0
Classifier: Programming Language :: Python :: 3
Classifier: Programming Language :: Python :: 3.9
Requires-Dist: openpyxl (>=3.0.7,<4.0.0)
Requires-Dist: openpyxl-image-loader (>=1.0.5,<2.0.0)
Requires-Dist: pydantic (>=1.8.2,<2.0.0)
Requires-Dist: python-camel-model-infomoto (>=1.0.0,<2.0.0)
